<?xml version="1.0" encoding="UTF-8" standalone="no"?><Users><User><Jmeno>Ucitel</Jmeno><Heslo>Ucitel</Heslo></User><User><Jmeno>Student</Jmeno><Heslo>Student</Heslo></User><User><Jmeno>admin</Jmeno><Heslo>admin</Heslo></User><User><Jmeno>admin</Jmeno><Heslo>admin</Heslo></User><User><Jmeno>admin</Jmeno><Heslo>admin</Heslo></User><User><Jmeno>Lukas</Jmeno><Heslo>lukas</Heslo></User><User><Jmeno>Tom</Jmeno><Heslo>tom</Heslo></User><User><Jmeno>admin</Jmeno><Heslo>admin</Heslo></User><User><Jmeno>Tim</Jmeno><Heslo>tim</Heslo></User><User><Jmeno>lukas</Jmeno><Heslo>lukas</Heslo></User><User><Jmeno>pokus</Jmeno><Heslo>pokus</Heslo></User><User><Jmeno/><Heslo/><Vysledek>Nic</Vysledek></User><User><Jmeno>jouda</Jmeno><Heslo>1234</Heslo><Vysledek>Nic</Vysledek></User><User><Jmeno>klkalasa</Jmeno><Heslo>123</Heslo><Vysledek>Nic</Vysledek></User></Users>